{
    "Ar36": {
        "error": 0.00030567224567646555, 
        "filter_outliers_dict": {
            "filter_outliers": true, 
            "iterations": 1, 
            "std_devs": 2
        }, 
        "fit": "Linear", 
        "value": 0.014061140060547643
    }, 
    "Ar37": {
        "error": 0.011937988131111845, 
        "filter_outliers_dict": {
            "filter_outliers": true, 
            "iterations": 1, 
            "std_devs": 2
        }, 
        "fit": "linear", 
        "value": 0.15592405698111997
    }, 
    "Ar38": {
        "error": 0.004551604845634273, 
        "filter_outliers_dict": {
            "filter_outliers": true, 
            "iterations": 1, 
            "std_devs": 2
        }, 
        "fit": "linear", 
        "value": 0.6971334987733588
    }, 
    "Ar39": {
        "error": 0.017379735186113444, 
        "filter_outliers_dict": {
            "filter_outliers": true, 
            "iterations": 1, 
            "std_devs": 2
        }, 
        "fit": "Linear", 
        "value": 54.29193767953304
    }, 
    "Ar40": {
        "error": 0.037057820517102553, 
        "filter_outliers_dict": {
            "filter_outliers": true, 
            "iterations": 1, 
            "std_devs": 2
        }, 
        "fit": "Linear", 
        "value": 569.6904402959599
    }, 
    "PM41": {
        "error": 0.06647331762774904, 
        "filter_outliers_dict": {
            "filter_outliers": false, 
            "iterations": 1, 
            "std_devs": 2
        }, 
        "fit": "linear", 
        "value": -0.1343849998440313
    }
}