{
    "Ar36": {
        "error": 0.002816817500920965, 
        "filter_outliers_dict": {
            "filter_outliers": true, 
            "iterations": 1, 
            "std_devs": 2
        }, 
        "fit": "Linear", 
        "value": 1.4421398853747027
    }, 
    "Ar37": {
        "error": 0.01084525654266482, 
        "filter_outliers_dict": {
            "filter_outliers": true, 
            "iterations": 1, 
            "std_devs": 2
        }, 
        "fit": "linear", 
        "value": 0.33143163317616764
    }, 
    "Ar38": {
        "error": 0.005001767451312071, 
        "filter_outliers_dict": {
            "filter_outliers": true, 
            "iterations": 1, 
            "std_devs": 2
        }, 
        "fit": "linear", 
        "value": 2.4643947321287873
    }, 
    "Ar39": {
        "error": 0.02315320170614097, 
        "filter_outliers_dict": {
            "filter_outliers": true, 
            "iterations": 1, 
            "std_devs": 2
        }, 
        "fit": "Linear", 
        "value": 163.41959840373573
    }, 
    "Ar40": {
        "error": 0.09131660302011745, 
        "filter_outliers_dict": {
            "filter_outliers": true, 
            "iterations": 1, 
            "std_devs": 2
        }, 
        "fit": "Linear", 
        "value": 2127.5578214497095
    }, 
    "PM41": {
        "error": 0.08090077838597498, 
        "filter_outliers_dict": {
            "filter_outliers": false, 
            "iterations": 1, 
            "std_devs": 2
        }, 
        "fit": "linear", 
        "value": -0.023957820850519992
    }
}